main.py
easy_sqlitedb-1.0.dist-info/METADATA
easy_sqlitedb-1.0.dist-info/WHEEL
easy_sqlitedb-1.0.dist-info/top_level.txt
easy_sqlitedb-1.0.dist-info/RECORD
