Metadata-Version: 2.1
Name: easy-sqlitedb
Version: 1.0
Summary: db lib for more elegant code
Author: alwwwd
Classifier: Programming Language :: Python :: 3
Classifier: License :: OSI Approved :: MIT License
Classifier: Operating System :: OS Independent
Requires-Python: >=3.10
